{
  "main": {
    "name":"Jacob Powell",
    "occupation":"Full Stack Software Engineer",
    "description":"I create software that no one knows is there until it isn't",
    "image":"profilepic.jpg",
    "bio":"I'm a very people oriented person. I enjoy talking and working with others in a productive and thoughtful way in order to get things done in a fun and effective manner. I have many hobbies and interests, including playing card games, Soccer, Running, Gardening, and Programming of course!",
    "contactmessage":"If you wish to get into contact with me, please fill out your information here and I will get back to you as soon as I can!",
    "email": "jcbpowell12@gmail.com",
    "phone": "714-757-2277",
    "address":{
      "state":"Southern California"
    },
    "website": "https://tcginventory.com",
    "resumedownload":"https://resume.s3.amazonaws.com/Jacob_Powell_Resume.pdf",
    "social":[
      {
        "name":"github",
        "url":"https://github.com/scout2012",
        "className":"fa fa-github"
      },
      {
        "name":"linkedin",
        "url":"https://www.linkedin.com/in/jacob-powell-925571121/",
        "className":"fa fa-linkedin"
      },
      {
        "name":"twitter",
        "url":"https://twitter.com/scoutdude2012",
        "className":"fa fa-twitter"
      }
    ]
  },
  "resume":{
    "skillmessage":"I work with a wide variety of technologies! Here's some of my favorites in no particular order.",
    "education":[
      {
        "school":"California State University, Fullerton",
        "degree":"B.S. Computer Science",
        "graduated":"May 2021",
        "description":"Describe your experience at school, what you learned, what useful skills you have acquired etc."
      }
    ],
    "work":[
      {
        "company":"Taco Bell",
        "title":"Software Engineer",
        "years":"September 2020 - Present",
        "description":[
          "Created a Mock API for use in QA for performance testing with Typescript and deployed on AWS",
          "Built up testing suites and integration tests from the ground up"
        ]
      },
      {
        "company":"Taco Bell",
        "title":"Software Engineer Intern",
        "years":"June 2020 - Present",
        "description":[
          "Took web application from design to production in 10 weeks by leveraging Serverless technology through AWS and Python",
          "Met with team in daily standups to discuss work accomplished and work to be done for the day",
          "Demoed progress weekly to various managers from various teams such as Security and Operations"
        ]
      },
      {
        "company":"California State University, Fullerton",
        "title":"Student Research Assistant",
        "years":"September 2019 - Present",
        "description": [
          "Researched methods for aiding in Cancer Prognosis",
          "Used various methods such as recursive feature elimination to help reduce the amount of dimensions within a dataset",
          "Tested various machine learning models and measured effectiveness from each model to determine the most effective one to use"
        ]
      },
      {
        "company":"Quantum Automation",
        "title":"Software Engineer",
        "years":"July 2019 - February 2020",
        "description":[
          "Designed and built a software solution to transport over 500,000 points of data from RFID chips daily",
          "Saved thousands of dollars and dozens of man hours by pivoting the development of a software project into a different direction and executing on it"
        ]
      }
    ],
    "skills":[
      {
        "name":"Node.js",
        "image":"node.png"
      },
      {
        "name":"Git",
        "image":"git.png"
      },
      {
        "name":"ReactJs",
        "image":"react.png"
      },
      {
        "name":"Python",
        "image":"python.png"
      },
      {
        "name":"C++",
        "image":"c++.png"
      },
      {
        "name":"MySQL",
        "image":"mysql.png"
      }
    ]
  },
  "portfolio":{
    "projects": [
      {
        "title":"TCG Inventory",
        "category":"Virtual Magic: The Gathering inventory manager and price tracker",
        "image":"tcginventory.png",
        "url":"https://www.tcginventory.com"
      }
    ]
  }
}
